alicechess/__init__.py
alicechess/__main__.py
alicechess/__version__.py
alicechess/_moves_calculator.py
alicechess/bots.py
alicechess/game.py
alicechess/game_state.py
alicechess/pictures/BB.png
alicechess/pictures/BK.png
alicechess/pictures/BN.png
alicechess/pictures/BP.png
alicechess/pictures/BQ.png
alicechess/pictures/BR.png
alicechess/pictures/WB.png
alicechess/pictures/WK.png
alicechess/pictures/WN.png
alicechess/pictures/WP.png
alicechess/pictures/WQ.png
alicechess/pictures/WR.png
alicechess/pieces/__init__.py
alicechess/pieces/king.py
alicechess/pieces/pawn.py
alicechess/pieces/piece.py
alicechess/player.py
alicechess/position.py
alicechess/utils.py
alicechess/window.py
alicechess-3.0.0.dist-info/LICENSE
alicechess-3.0.0.dist-info/WHEEL
alicechess-3.0.0.dist-info/METADATA
alicechess-3.0.0.dist-info/RECORD
