Metadata-Version: 2.1
Name: alicechess
Version: 3.0.0
Summary: A Python package to play Alice Chess
Home-page: https://github.com/josephlou5/alicechess
License: MIT
Author: Joseph Lou
Author-email: joseph.d.lou@gmail.com
Requires-Python: >=3.11,<4.0
Classifier: License :: OSI Approved :: MIT License
Classifier: Programming Language :: Python :: 3
Classifier: Programming Language :: Python :: 3.11
Classifier: Programming Language :: Python :: 3.11
Classifier: Topic :: Games/Entertainment :: Board Games
Classifier: Topic :: Software Development :: Libraries :: Python Modules
Classifier: Typing :: Typed
Requires-Dist: Pillow (>=9.5.0,<10.0.0)
Project-URL: Repository, https://github.com/josephlou5/alicechess
